fds/__init__.py
fds/sdk/__init__.py
fds/sdk/UniversalScreening/__init__.py
fds/sdk/UniversalScreening/api_client.py
fds/sdk/UniversalScreening/configuration.py
fds/sdk/UniversalScreening/exceptions.py
fds/sdk/UniversalScreening/model_utils.py
fds/sdk/UniversalScreening/rest.py
fds/sdk/UniversalScreening/api/__init__.py
fds/sdk/UniversalScreening/api/job_management_api.py
fds/sdk/UniversalScreening/api/screening_operations_api.py
fds/sdk/UniversalScreening/apis/__init__.py
fds/sdk/UniversalScreening/model/__init__.py
fds/sdk/UniversalScreening/model/active_job_ids.py
fds/sdk/UniversalScreening/model/active_jobs_data.py
fds/sdk/UniversalScreening/model/calculate_metadata.py
fds/sdk/UniversalScreening/model/delimited_options.py
fds/sdk/UniversalScreening/model/error_array.py
fds/sdk/UniversalScreening/model/error_code.py
fds/sdk/UniversalScreening/model/error_object.py
fds/sdk/UniversalScreening/model/error_object_source.py
fds/sdk/UniversalScreening/model/excel_options.py
fds/sdk/UniversalScreening/model/grouping_info.py
fds/sdk/UniversalScreening/model/paginated_calculation_response.py
fds/sdk/UniversalScreening/model/pagination_response.py
fds/sdk/UniversalScreening/model/pdf_options.py
fds/sdk/UniversalScreening/model/resource_status_response.py
fds/sdk/UniversalScreening/model/resource_status_response_data.py
fds/sdk/UniversalScreening/model/results_metadata.py
fds/sdk/UniversalScreening/model/screen_archive_ofdb_parameters.py
fds/sdk/UniversalScreening/model/screen_archive_ofdb_parameters_data.py
fds/sdk/UniversalScreening/model/screen_archive_ofdb_parameters_data_archive_options.py
fds/sdk/UniversalScreening/model/screen_calc_parameters.py
fds/sdk/UniversalScreening/model/screen_calc_parameters_data.py
fds/sdk/UniversalScreening/model/screen_export_parameters.py
fds/sdk/UniversalScreening/model/screen_export_parameters_data.py
fds/sdk/UniversalScreening/model/submit_export_response.py
fds/sdk/UniversalScreening/model/submit_export_response_data.py
fds_sdk_universalscreening-1.3.0.dist-info/licenses/LICENSE
fds_sdk_universalscreening-1.3.0.dist-info/METADATA
fds_sdk_universalscreening-1.3.0.dist-info/WHEEL
fds_sdk_universalscreening-1.3.0.dist-info/top_level.txt
fds_sdk_universalscreening-1.3.0.dist-info/RECORD
